{
  "version": 2,
  "name": "statickit-site",
  "scope": "unstacked",
  "builds": [{ "src": "package.json", "use": "@now/next" }],
  "routes": [
    {
      "src": "/docs/config/schema",
      "status": 308,
      "headers": { "Location": "/docs/config" }
    },
    {
      "src": "/forms",
      "status": 308,
      "headers": { "Location": "/contact-forms" }
    },
    {
      "src": "/docs/html",
      "status": 308,
      "headers": { "Location": "/docs/forms/html" }
    },
    {
      "src": "/docs/html/forms",
      "status": 308,
      "headers": { "Location": "/docs/forms/html" }
    },
    {
      "src": "/docs/react",
      "status": 308,
      "headers": { "Location": "/docs/forms/react" }
    },
    {
      "src": "/static/fonts/(.*)",
      "headers": { "cache-control": "public, max-age=31536000" },
      "dest": "/static/fonts/$1"
    }
  ]
}
